nucleopy/__init__.py
nucleopy/models/__init__.py
nucleopy/models/cnn.py
nucleopy/models/dnn.py
nucleopy/molecules/__init__.py
nucleopy/molecules/dna.py
nucleopy/molecules/nucleotide.py
nucleopy/molecules/rna.py
nucleopy-0.1.0.dist-info/LICENSE
nucleopy-0.1.0.dist-info/METADATA
nucleopy-0.1.0.dist-info/WHEEL
nucleopy-0.1.0.dist-info/top_level.txt
nucleopy-0.1.0.dist-info/RECORD
