Metadata-Version: 2.1
Name: nucleopy
Version: 0.1.0
Summary: A library for creating and manipulating RNA and DNA sequences
Home-page: https://github.com/RK900/nucleopy
Author: Rohan Koodli
Author-email: rovik05@gmail.com
License: UNKNOWN
Platform: UNKNOWN
Classifier: Programming Language :: Python :: 3
Classifier: Programming Language :: Python :: 2
Classifier: License :: OSI Approved :: MIT License
Classifier: Operating System :: OS Independent
